<?xml version="1.0" encoding="utf-8"?>
<odoo>
  <data>
    <template id="runbot.glances">
      <t t-call='portal.frontend_layout'>
        <t t-set="head">
          <t t-if="refresh">
            <meta http-equiv="refresh" t-att-content="refresh"/>
          </t>
        </t>
        <div class="container-fluid">
          <div class="row">
            <div class='col-md-12'>
              <div>
                <span t-attf-class="badge badge-{{pending_level}}">
                  Pending:
                  <t t-esc="pending_total"/>
                </span>
              </div>
              <t t-set="project_id"/>
              <t t-set="nb_project" t-value="len(bundles.mapped('project_id'))"/>
              <t t-foreach="bundles.sorted(lambda b: (-b.project_id.id, b.version_id.number), reverse=True)" t-as="bundle">
                <h3 t-if="nb_project > 1 and project_id != bundle.project_id.id" t-esc="bundle.project_id.name"/>
                <t t-set="project_id" t-value="bundle.project_id.id"/>
                <h4>
                  <t t-esc="bundle.name"/>
                </h4>
                <t t-foreach="bundle.last_done_batch.slot_ids" t-as="slot">
                  <span t-attf-class="badge badge-{{slot.build_id.get_color_class()}}">
                    <t t-esc="slot.trigger_id.name"/>
                  </span>
                </t>
              </t>
            </div>
          </div>
        </div>
      </t>
    </template>

    <template id="frontend_no_nav" inherit_id="portal.frontend_layout" primary="True">
      <xpath expr="//header" position="replace">
      </xpath>
    </template>

    <template id="runbot.config_monitoring">
      <t t-call="runbot.frontend_no_nav">
        <t t-set="head">
          <t t-if="refresh">
            <meta http-equiv="refresh" t-att-content="refresh"/>
          </t>
        </t>
      </t>
    </template>

    <template id="runbot.monitoring">
      <t t-call="runbot.frontend_no_nav">
        <t t-set="head">
          <t t-if="refresh">
            <meta http-equiv="refresh" t-att-content="refresh"/>
          </t>
          <style>
            h4 {
            padding: 3px 0;
            border-bottom: 1px solid grey;
            }
            .r-mb02 { margin-bottom: 0.2em; }
          </style>
        </t>
        <div class="container-fluid">
          <div class="row">
            <div class="col-md-12">
              <div>
                <t t-call="runbot.slots_infos"/>
              </div>
              <t t-foreach="hosts_data.sorted(key=lambda h:h.name)" t-as="host">
                <div>
                  <span t-esc="host.name.split('.')[0]"/>
                  <t t-if="host.nb_testing == 0">
                    <t t-set="klass">success</t>
                  </t>
                  <t t-if="host.nb_testing > 0">
                    <t t-set="klass">info</t>
                  </t>
                  <t t-if="host.nb_testing == host.nb_worker">
                    <t t-set="klass">warning</t>
                  </t>
                  <t t-if="host.nb_testing > host.nb_worker">
                    <t t-set="klass">danger</t>
                  </t>
                  <span t-attf-class="badge badge-{{klass}}">
                    <span t-esc="host.nb_testing"/>
                    /
                    <span t-esc="host.nb_worker"/>
                  </span>
                  <t t-esc="host.nb_running"/>
                  <t t-set="succes_time" t-value="int(datetime.datetime.now().timestamp() - host.last_success.timestamp())"/>
                  <t t-set="start_time" t-value="int(datetime.datetime.now().timestamp() - host.last_start_loop.timestamp())"/>
                  <t t-set="end_time" t-value="int(datetime.datetime.now().timestamp() - host.last_end_loop.timestamp())"/>

                  <t t-set="klass">success</t>
                  <t t-if="succes_time > 30">
                    <t t-set="klass">info</t>
                  </t>
                  <t t-if="succes_time > 180">
                    <t t-set="klass">danger</t>
                  </t>

                  <span t-attf-class="badge badge-{{klass}}">
                    <span t-esc="succes_time"/>
                  </span>

                  <t t-set="klass">success</t>
                  <t t-if="start_time > 60*10">
                    <t t-set="klass">info</t>
                  </t>
                  <t t-if="start_time > 60*15">
                    <t t-set="klass">danger</t>
                  </t>

                  <span t-attf-class="badge badge-{{klass}}">
                    <span t-esc="start_time"/>
                  </span>

                  <t t-set="klass">success</t>
                  <t t-if="end_time > 60*10">
                    <t t-set="klass">info</t>
                  </t>
                  <t t-if="end_time > 60*15">
                    <t t-set="klass">danger</t>
                  </t>

                  <span t-attf-class="badge badge-{{klass}}">
                    <span t-esc="end_time"/>
                  </span>

                  <t t-set="cron_time" t-value="end_time-start_time"/>
                  <t t-set="klass">success</t>
                  <t t-if="abs(cron_time) > 10">
                    <t t-set="klass">info</t>
                  </t>
                  <t t-if="abs(cron_time) > 60">
                    <t t-set="klass">danger</t>
                  </t>
                  <span t-attf-class="badge badge-{{klass}}">
                    <span t-esc="cron_time"/>
                  </span>

                </div>
              </t>

              <table>
                <tr t-foreach="bundles.sorted(lambda b: b.version_id.number, reverse=True)" t-as="bundle">
                  <td>
                    <t t-esc="bundle.version_id.number"/>
                  </td>
                  <td>
                    <t t-set='batch' t-value="bundle.with_context({'category_id': category.id}).last_done_batch"/>
                    <table>
                      <t t-foreach="batch.slot_ids" t-as='slot'>
                        <tr>
                          <td>
                            <t t-esc="slot.trigger_id.name[:4]"/>
                          </td>
                          <t t-set="build" t-value="slot.build_id"/>
                          <td>
                            <span t-attf-class="badge badge-{{slot.build_id.get_color_class()}}">
                              <i t-attf-class="fa fa-{{category.icon}}"/>
                            </span>
                          </td>
                          <td t-foreach="build.children_ids" t-as="child">
                            <span t-attf-class="badge badge-{{slot.build_id.get_color_class()}}">
                              <t t-esc="child.params_id.config_id.name[:4]"/>
                            </span>
                          </td>
                        </tr>
                      </t>
                    </table>
                  </td>
                </tr>
              </table>
            </div>
          </div>
        </div>
      </t>
    </template>

    <template id="runbot.default_dashboard_tile_view">
      <div class="col-sm-3">
        <div class="card">
          <div class="card-header">
            <t t-esc="tile.display_name"/>
          </div>
          <div class="card-body">
            <p t-if="not tile.build_ids" class="text-success my-0">No build found 👍</p>
            <t t-foreach="tile.sticky_bundle_ids.sorted(lambda b: b.version_id.number, reverse=True)" t-as="bundle">
              <t t-set="failed_builds" t-value="tile.build_ids.filtered(lambda b: b.top_parent.slot_ids.batch_id.bundle_id == bundle)"/>
              <h4 class="card-title" t-if="failed_builds" t-esc="bundle.name"/>
              <p t-foreach="failed_builds" t-as="build" class="my-0">
                  <a class="text-danger" t-attf-href="/runbot/build/{{build.id}}" target="new">
                    <t t-esc="build.description or build.id"/>
                  </a>
              </p>
            </t>
          </div>
        </div>
      </div>
    </template>

    <template id="runbot.dashboard">
      <div class="row">
        <t t-foreach="dashboard.dashboard_tile_ids" t-as="tile">
          <t t-if="tile.build_ids or not hide_empty" t-call="{{ tile.custom_template_id.id }}"/>
        </t>
      </div>
    </template>

    <template id="runbot.dashboard_page">
      <t t-call="runbot.frontend_no_nav">
        <t t-set="head">
          <t t-if="refresh">
            <meta http-equiv="refresh" t-att-content="refresh"/>
          </t>
        </t>
        <t t-call="runbot.dashboard"/>
      </t>
    </template>

  </data>
</odoo>
