<?xml version="1.0" encoding="utf-8"?>
<odoo>
    <data>
      <!-- Replace default menu ( Home / Contactus and co...) with 5 first repos) -->
      <template id="inherits_branch_in_menu" inherit_id="website.layout" name="Inherits Show top 5 branches in menu">
          <xpath expr="//t[@t-foreach=&quot;website.menu_id.child_id&quot;][@t-as=&quot;submenu&quot;]" position="replace">
              <t t-if="repos" >
                   <t t-foreach="repos[:5]" t-as="re">
                       <li><a t-attf-href="/runbot/repo/{{slug(re)}}?search={{request.params.get('search', '')}}"><i class='fa fa-github' /> <t t-esc="re.short_name"/></a></li>
                   </t>
              </t>
          </xpath>
      </template>

      <!-- remove black bar with app switcher -->
      <template id="inherits_no_black_bar" inherit_id="website.user_navbar" name="Inherits No black user_navbar">
          <xpath expr="//nav[@id='oe_main_menu_navbar']" position="attributes">
              <attribute name="groups">base.group_website_publisher</attribute>
          </xpath>
          <xpath expr="//t[@t-set='body_classname']" position="attributes">
              <attribute name="t-value">'o_connected_user' if env['ir.ui.view'].user_has_groups('base.group_website_publisher') else None</attribute>
          </xpath>
      </template>
      <!-- Frontend repository block -->
      <template id="runbot.repo">
          <t t-call='website.layout'>
              <t t-set="head">
                  <t t-if="refresh">
                      <meta http-equiv="refresh" t-att-content="refresh"/>
                  </t>
                  <style>
                    .killed {
                      background-color: #aaa;
                    }
                  </style>
              </t>
              <div class="container-fluid">
                  <div class="row">
                      <div class='col-md-12'>
                          <nav class="navbar navbar-default" role="navigation">
                            <div class="container-fluid">
                              <div class="navbar-header">
                                <button type="button" class="navbar-toggle" data-toggle="collapse" data-target="#bs-example-navbar-collapse-1">
                                  <span class="sr-only">Toggle navigation</span>
                                  <span class="icon-bar"></span>
                                  <span class="icon-bar"></span>
                                  <span class="icon-bar"></span>
                                </button>
                                <t t-if="repo">
                                    <ul class="nav navbar-nav">
                                      <li class="dropdown">
                                        <a href="#" class="dropdown-toggle" data-toggle="dropdown" aria-expanded="false"><b style="font-size: 18px;"><t t-esc="repo.base"/></b><b class="caret"></b></a>
                                        <ul class="dropdown-menu">
                                          <t t-foreach='repos' t-as='re'>
                                              <li><a t-attf-href="/runbot/repo/{{slug(re)}}"><t t-esc="re.base"/></a></li>
                                          </t>
                                        </ul>
                                      </li>
                                    </ul>

                                </t>
                              </div>
                              <div class="collapse navbar-collapse" id="bs-example-navbar-collapse-1">
                                <t t-if="repo">
                                  <form class="navbar-form navbar-right" role="search" t-att-action="qu(search='')" method="get">
                                    <div class="form-group">
                                      <input type="search" name="search" class="form-control" placeholder="Search" t-att-value="search"/>
                                      <button type="submit" class="btn btn-default">Search</button>
                                    </div>
                                  </form>
                                </t>
                              </div>
                              <p class="text-center">
                                  <t  t-foreach="host_stats" t-as="hs">
                                  <span class="label label-default">
                                      <t t-esc="hs['host']"/>: <t t-esc="hs['testing']"/> testing
                                  </span>&amp;nbsp;
                                  </t>
                                  <span t-attf-class="label label-{{pending_level}}">Pending: <t t-esc="pending_total"/></span>
                              </p>
                            </div>
                          </nav>
                          <div t-if="message" class="alert alert-warning" role="alert">
                            <t t-esc="message" />
                          </div>
                          <div t-if="not repo" class="mb32">
                              <h1>No Repository yet.</h1>
                          </div>

                          <table t-if="repo" class="table table-condensed table-bordered" style="table-layout: initial;">
                          <tr>
                              <th>Branch</th>
                              <td colspan="4" class="text-right">
                                  <t t-esc="repo.base"/>: 
                                  <t t-esc="testing"/> testing,
                                  <t t-esc="running"/> running,
                                  <t t-esc="pending"/> pending.
                              </td>

                          </tr>
                          <tr t-foreach="branches" t-as="br">
                              <td>
                                  <i t-if="br['branch'].sticky" class="fa fa-star" style="color: #f0ad4e" />
                                  <a t-attf-href="/runbot/branch/#{br['branch'].id}"><b t-esc="br['branch'].branch_name"/></a>
                                  <small><t t-esc="br['builds'] and br['builds'][0].get_formated_build_time()"/></small><br/>
                                  <div class="btn-group btn-group-xs">
                                      <a t-attf-href="{{br['branch'].branch_url}}" class="btn btn-default btn-xs">Branch or pull <i class="fa fa-github"/></a>
                                      <a t-attf-href="/runbot/quick_connect/#{br['branch'].id}" class="btn btn-default btn-xs" aria-label="Quick Connect"><i class="fa fa-fast-forward" title="Quick Connect"/></a>
                                  </div>
                                  <t t-if="br['branch'].sticky">
                                      <br/>
                                      <t t-if="br['branch'].coverage_result > 0">
                                        <t t-set="last_build" t-value="br['branch']._get_last_coverage_build()" />
                                        <a t-attf-href="http://{{last_build.real_build.host}}/runbot/static/build/#{last_build['dest']}/coverage/index.html">
                                        <span class="label label-info">cov: <t t-esc="br['branch'].coverage_result"/>%</span>
                                      </a>
                                      </t>
                                      <t t-else="">
                                        <span class="label label-info">cov: <t t-esc="br['branch'].coverage_result"/>%</span>
                                      </t>
                                  </t>
                                  <t t-if="br['branch'].branch_config_id"><!--custom config on branch-->
                                    <br/>
                                    <span class="label label-info"><t t-esc="br['branch'].branch_config_id.name" t-att-title="br['branch'].branch_config_id.description"/></span>
                                  </t>
                              </td>
                              <t t-foreach="br['builds']" t-as="bu">
                                  <t t-if="bu.global_state=='pending'"><t t-set="klass">default</t></t>
                                  <t t-if="bu.global_state in ('testing', 'waiting')"><t t-set="klass">info</t></t>
                                  <t t-if="bu.global_state in ['running','done']">
                                    <t t-if="bu.global_result == 'ko'"><t t-set="klass">danger</t></t>
                                    <t t-if="bu.global_result == 'warn'"><t t-set="klass">warning</t></t>
                                    <t t-if="bu.global_result == 'ok'"><t t-set="klass">success</t></t>
                                    <t t-if="bu.global_result == 'skipped'"><t t-set="klass">default</t></t>
                                    <t t-if="bu.global_result in ['killed', 'manually_killed']"><t t-set="klass">killed</t></t>
                                  </t>
                                  <td t-attf-class="{{klass}}">
                                     <t t-call="runbot.build_button">
                                      <t t-set="klass">btn-group-sm</t>
                                      <t t-set="show_rebuild_button" t-value="bu==br['builds'][0]"></t>
                                     </t>
                                     <t t-if="bu['build_type']=='scheduled'"><i class="fa fa-moon-o" t-att-title="bu.build_type_label()" t-att-aria-label="bu.build_type_label()"/></t>
                                     <t t-if="bu['build_type'] in ('rebuild', 'indirect')"><i class="fa fa-recycle" t-att-title="bu.build_type_label()" t-att-aria-label="bu.build_type_label()"/></t>
                                     <t t-if="bu['subject']">
                                          <t t-if="bu.config_id != bu.branch_id.config_id">
                                            <b t-esc="bu.config_id.name"/>
                                          </t>
                                          <span t-esc="bu['subject'][:32] + ('...' if bu['subject'][32:] else '') " t-att-title="bu['subject']"/>
                                           <br/>
                                      </t>
                                     <t t-id="bu['author']">
                                          <t t-esc="bu['author']"/>
                                          <t t-if="bu['committer'] and bu['author'] != bu['committer']" t-id="bu['committer']">
                                              (<span class="octicon octicon-arrow-right"></span>&amp;nbsp;<t t-esc="bu['committer']"/>)
                                          </t>
                                          <br/>
                                      </t>
                                      <small><t t-esc="bu['dest']"/> on <t t-esc="bu.real_build.host"/></small><br/>
                                      <t t-call="runbot.build_name"/>
                                  </td>
                              </t>
                          </tr>
                          </table>
                      </div>
                  </div>

              </div>
          </t>
      </template>
    </data>
</odoo>
